dlchord2/__init__.py
dlchord2/accidentals.py
dlchord2/chord.py
dlchord2/const.py
dlchord2/note.py
dlchord2/quality.py
dlchord2/scale.py
dlchord2/utils.py
dlchord2/exceptions/__init__.py
dlchord2/exceptions/accidentals_exceptions.py
dlchord2/exceptions/note_exceptions.py
dlchord2/exceptions/quality_exceptions.py
dlchord2/exceptions/scale_exceptions.py
dlchord2/parser/__init__.py
dlchord2/parser/accidentals_parser.py
dlchord2/parser/chord_parser.py
dlchord2/parser/note_parser.py
dlchord2/parser/quality_parser.py
test/__init__.py
test/test_accidentals.py
test/test_accidentals_parser.py
test/test_chord.py
test/test_chord_parser.py
test/test_note.py
test/test_note_parser.py
test/test_quality.py
test/test_quality_parser.py
test/test_scale.py
test/test_utils.py
dlchord2-0.0.7.dist-info/LICENSE
dlchord2-0.0.7.dist-info/METADATA
dlchord2-0.0.7.dist-info/WHEEL
dlchord2-0.0.7.dist-info/top_level.txt
dlchord2-0.0.7.dist-info/RECORD
