Metadata-Version: 2.1
Name: dlchord2
Version: 0.0.7
Summary: chord library
Home-page: https://github.com/anime-song/DLChord2
Author: anime-song
License: MIT
Keywords: music chord
License-File: LICENSE
